__init__.py
app.py
main.py
server.py
util.py
images/CCS1.png
images/J1772.png
images/tesla.png
where2charge/__init__.py
where2charge/recommender.py
where2charge/logic/__init__.py
where2charge/logic/analyzer.py
where2charge/logic/data_handler.py
where2charge/logic/googleAPI_handler.py
where2charge/logic/text_analyzer.py
where2charge/logic/data/EVregistration.csv
where2charge/logic/data/Electric_Vehicle_Population_Data.csv
where2charge/logic/data/TRACT_2020_90_20_PL.cpg
where2charge/logic/data/TRACT_2020_90_20_PL.dbf
where2charge/logic/data/TRACT_2020_90_20_PL.prj
where2charge/logic/data/TRACT_2020_90_20_PL.shp
where2charge/logic/data/TRACT_2020_90_20_PL.shp.xml
where2charge/logic/data/TRACT_2020_90_20_PL.shx
where2charge/logic/data/alt_fuel_stations_updated.csv
where2charge/logic/data/geo_df.csv
where2charge/logic/data/merged_df.csv
where2charge-1.0.0.dist-info/LICENSE
where2charge-1.0.0.dist-info/METADATA
where2charge-1.0.0.dist-info/WHEEL
where2charge-1.0.0.dist-info/top_level.txt
where2charge-1.0.0.dist-info/RECORD
