Metadata-Version: 2.1
Name: where2charge
Version: 1.0.0
Summary: where2charge - an EV charging station recommender system
Author-email: Soheil Keshavarz <soheil99@uw.edu>, Arsalan Esmaili <arsalan@uw.edu>
Project-URL: Homepage, https://github.com/BlueSoheil99/where2charge.git
Project-URL: Issues, https://github.com/BlueSoheil99/where2charge/issues
Keywords: Electric vehicle,charging station,suggestion,recommendation,EV,EVCS,Google Maps API,Openai API
Classifier: Development Status :: 3 - Alpha
Classifier: Programming Language :: Python :: 3
Classifier: Framework :: FastAPI
Classifier: License :: OSI Approved :: MIT License
Classifier: Operating System :: OS Independent
Requires-Python: >=3.12
License-File: LICENSE
Requires-Dist: fastapi==0.112
Requires-Dist: folium==0.14
Requires-Dist: numpy==1.26
Requires-Dist: openai==1.52
Requires-Dist: pandas==2.2
Requires-Dist: pylint==3.2
Requires-Dist: python==3.12
Requires-Dist: pyyaml==6.0
Requires-Dist: streamlit==1.38
Requires-Dist: uvicorn==0.30
Requires-Dist: yaml==0.2
Requires-Dist: googlemaps==4.10
Requires-Dist: geopandas
Requires-Dist: shapely
Requires-Dist: pytest
Requires-Dist: streamlit-folium==0.23
Requires-Dist: livepopulartimes==1.3
Requires-Dist: streamlit-image-select==0.6
